SibylSystem/__init__.py
SibylSystem/exceptions.py
SibylSystem/types/__init__.py
SibylSystem/types/bans.py
SibylSystem/types/error.py
SibylSystem/types/general_info.py
SibylSystem/types/permission.py
SibylSystem/types/report.py
SibylSystem/types/stats.py
SibylSystem/types/token.py
sibylsystem-0.0.25.dist-info/LICENSE
sibylsystem-0.0.25.dist-info/METADATA
sibylsystem-0.0.25.dist-info/WHEEL
sibylsystem-0.0.25.dist-info/RECORD
