Metadata-Version: 2.1
Name: SibylSystem
Version: 0.0.25
Summary: Python Wrapper for the Sibyl System Antispam API for telegram
Home-page: https://github.com/MinistryOfWelfare/SibylSystem-Py
Keywords: sibyl,wrapper,telegram,antispam,api
Author: Sayan
Author-email: dank@kaizoku.cyou
Requires-Python: >=3.7,<4.0
Classifier: License :: OSI Approved :: GNU General Public License v3 (GPLv3)
Classifier: Operating System :: OS Independent
Classifier: Programming Language :: Python :: 3
Classifier: Programming Language :: Python :: 3.7
Classifier: Programming Language :: Python :: 3.8
Classifier: Programming Language :: Python :: 3.9
Classifier: Programming Language :: Python :: 3.10
Classifier: Programming Language :: Python :: 3.11
Requires-Dist: httpx (>=0.20.0)
Requires-Dist: pydantic (>=1.8.2)
